app/__init__.py
app/main.py
app/api/__init__.py
app/api/api_v1/__init__.py
app/api/api_v1/api.py
app/api/api_v1/endpoints/__init__.py
app/api/api_v1/endpoints/webhook.py
app/api/api_v1/endpoints/zap_protocol.py
app/cli/__init__.py
app/cli/integrate.py
app/core/__init__.py
app/core/config.py
app/core/lifespan.py
app/core/security.py
app/models/__init__.py
app/models/internal_state.py
app/models/whatsapp.py
app/services/__init__.py
app/services/webhook_processor.py
app/utils/__init__.py
app/utils/http_client.py
app/utils/redis_client.py
app/zap_mcp_server/__init__.py
app/zap_mcp_server/completions.py
app/zap_mcp_server/context_manager.py
app/zap_mcp_server/instance.py
app/zap_mcp_server/protocol.py
app/zap_mcp_server/session_manager.py
app/zap_mcp_server/stdio_client.py
app/zap_mcp_server/tenant_settings.py
ragazap-0.1.0.dist-info/licenses/LICENSE
ragazap-0.1.0.dist-info/METADATA
ragazap-0.1.0.dist-info/WHEEL
ragazap-0.1.0.dist-info/entry_points.txt
ragazap-0.1.0.dist-info/top_level.txt
ragazap-0.1.0.dist-info/RECORD
