Metadata-Version: 2.4
Name: ragazap
Version: 0.1.0
Summary: WhatsApp Multi-Capability Protocol (MCP) Server
Author-email: JQuant Team <info@jquant.com>
License: MIT
Project-URL: Homepage, https://github.com/jquant/whatsapp-mcp-server
Project-URL: Bug Tracker, https://github.com/jquant/whatsapp-mcp-server/issues
Classifier: Development Status :: 4 - Beta
Classifier: Intended Audience :: Developers
Classifier: License :: OSI Approved :: MIT License
Classifier: Programming Language :: Python :: 3
Classifier: Programming Language :: Python :: 3.8
Classifier: Programming Language :: Python :: 3.9
Classifier: Programming Language :: Python :: 3.10
Classifier: Programming Language :: Python :: 3.11
Requires-Python: >=3.8
License-File: LICENSE
Requires-Dist: fastapi>=0.115.0
Requires-Dist: mcp>=1.6.0
Requires-Dist: pydantic>=2.0.0
Requires-Dist: uvicorn>=0.17.0
Requires-Dist: redis>=4.5.0
Requires-Dist: httpx>=0.24.0
Requires-Dist: loguru>=0.6.0
Provides-Extra: dev
Requires-Dist: pytest>=7.0.0; extra == "dev"
Requires-Dist: black>=23.0.0; extra == "dev"
Requires-Dist: isort>=5.12.0; extra == "dev"
Requires-Dist: build>=1.0.0; extra == "dev"
Requires-Dist: twine>=4.0.0; extra == "dev"
Dynamic: license-file
